Metadata-Version: 1.0
Name: mandelbrot-orbit
Version: 1.1.0
Summary: Python command line application to generate graphs of Mandelbrot Set point orbits.
Home-page: https://github.com/josecelano/mandelbrot-orbit
Author: Jose Celano
Author-email: josecelano@gmail.com
License: UNKNOWN
Platform: UNKNOWN
